ubox360/__about__.py
ubox360/__init__.py
ubox360/__main__.py
ubox360/gamepad.py
ubox360/types.py
ubox360/ubox360.py
ubox360-0.3.0.dist-info/LICENSE.md
ubox360-0.3.0.dist-info/METADATA
ubox360-0.3.0.dist-info/WHEEL
ubox360-0.3.0.dist-info/entry_points.txt
ubox360-0.3.0.dist-info/top_level.txt
ubox360-0.3.0.dist-info/RECORD
