Metadata-Version: 2.1
Name: ubox360
Version: 0.3.0
Summary: A tool to map joystick events to the one of an Xbox 360 controller
Home-page: https://gitlab.com/albinou/python-ubox360
Author: Albin Kauffmann
Author-email: albin@kauff.org
License: UNKNOWN
Project-URL: Bug Reports, https://gitlab.com/albinou/python-ubox360/issues
Project-URL: Source, https://gitlab.com/albinou/python-ubox360
Keywords: gamepad joystick Xbox Xbox360 controller
Platform: UNKNOWN
Classifier: Development Status :: 4 - Beta
Classifier: Intended Audience :: End Users/Desktop
Classifier: Topic :: Games/Entertainment
Classifier: License :: OSI Approved :: GNU General Public License v3 or later (GPLv3+)
Classifier: Programming Language :: Python :: 3
Classifier: Programming Language :: Python :: 3.5
Classifier: Programming Language :: Python :: 3.6
Classifier: Programming Language :: Python :: 3.7
Classifier: Programming Language :: Python :: 3.8
Classifier: Programming Language :: Python :: 3 :: Only
Requires-Python: >=3.5, <4
Requires-Dist: evdev
